{"result":"success","KmClinicDetailView":[{"followNum":0,"keywordList":["M자탈모","열성","원형","지루성 탈모"],"bigRegionCode":"1","linePhone":" 02-3473-7010 ","bigRegionName":"서울","type":2,"homepage":"https://www.balmers.co.kr:506/","remainRegion":"테헤란로14길 6 602호(역삼동, 남도빌딩)","id":1,"middleRegionName":"강남구","details":"","kmClinicPictureList":[{"id":0,"order":0,"picturePath":"face10.png","kmClinicId":0},{"id":0,"order":0,"picturePath":"face11.png","kmClinicId":0},{"id":0,"order":0,"picturePath":"face12.png","kmClinicId":0},{"id":0,"order":0,"picturePath":"face13.png","kmClinicId":0},{"id":0,"order":0,"picturePath":"face14.png","kmClinicId":0},{"id":0,"order":0,"picturePath":"face15.png","kmClinicId":0},{"id":0,"order":0,"picturePath":"face1.png","kmClinicId":0},{"id":0,"order":0,"picturePath":"face2.png","kmClinicId":0},{"id":0,"order":0,"picturePath":"face3.png","kmClinicId":0},{"id":0,"order":0,"picturePath":"face4.png","kmClinicId":0},{"id":0,"order":0,"picturePath":"face5.png","kmClinicId":0},{"id":0,"order":0,"picturePath":"face6.png","kmClinicId":0},{"id":0,"order":0,"picturePath":"face7.png","kmClinicId":0},{"id":0,"order":0,"picturePath":"face8.png","kmClinicId":0},{"id":0,"order":0,"picturePath":"face9.png","kmClinicId":0}],"middleRegionCode":"23","name":" 강남발머스한의원 ","userSimpleInfoList":[{"picturePath":"face1.png","email":"user1@gmail.com","name":"남태일"}]}]}